{
    "targets": [
        "pollen",
        "pollen-flower",
        "pollen-grass",
        "pollen-grass-high",
        "pollen-grass-low",
        "pollen-grass-moderate",
        "pollen-grass-very-high",
        "pollen-tree",
        "pollen-tree-fir",
        "pollen-tree-high",
        "pollen-tree-low",
        "pollen-tree-moderate",
        "pollen-tree-very-high",
        "pollen-weed",
        "pollen-weed-high",
        "pollen-weed-low",
        "pollen-weed-moderate",
        "pollen-weed-very-high"
    ],
    "layers": {
        "Pollen 7": {
            "animations": [
                {
                    "transform": "translate",
                    "values": [
                        0,
                        0,
                        8,
                        -4
                    ],
                    "duration": "3s",
                    "easing": "ease-in-out",
                    "delay": 0
                },
                {
                    "property": "opacity",
                    "values": [
                        0,
                        1,
                        1,
                        0
                    ],
                    "keyTimes": [
                        0,
                        0.2,
                        0.8,
                        1
                    ],
                    "duration": "3s",
                    "delay": 0
                }
            ]
        },
        "Pollen 6": {
            "animations": [
                {
                    "transform": "translate",
                    "values": [
                        0,
                        0,
                        8,
                        -4
                    ],
                    "duration": "3s",
                    "easing": "ease-in-out",
                    "delay": 0.35
                },
                {
                    "property": "opacity",
                    "values": [
                        0,
                        1,
                        1,
                        0
                    ],
                    "keyTimes": [
                        0,
                        0.2,
                        0.8,
                        1
                    ],
                    "duration": "3s",
                    "delay": 0.35
                }
            ]
        },
        "Pollen 5": {
            "animations": [
                {
                    "transform": "translate",
                    "values": [
                        0,
                        0,
                        8,
                        -4
                    ],
                    "duration": "3s",
                    "easing": "ease-in-out",
                    "delay": 0.7
                },
                {
                    "property": "opacity",
                    "values": [
                        0,
                        1,
                        1,
                        0
                    ],
                    "keyTimes": [
                        0,
                        0.2,
                        0.8,
                        1
                    ],
                    "duration": "3s",
                    "delay": 0.7
                }
            ]
        },
        "Pollen 4": {
            "animations": [
                {
                    "transform": "translate",
                    "values": [
                        0,
                        0,
                        8,
                        -4
                    ],
                    "duration": "3s",
                    "easing": "ease-in-out",
                    "delay": 1.0499999999999998
                },
                {
                    "property": "opacity",
                    "values": [
                        0,
                        1,
                        1,
                        0
                    ],
                    "keyTimes": [
                        0,
                        0.2,
                        0.8,
                        1
                    ],
                    "duration": "3s",
                    "delay": 1.0499999999999998
                }
            ]
        },
        "Pollen 3": {
            "animations": [
                {
                    "transform": "translate",
                    "values": [
                        0,
                        0,
                        8,
                        -4
                    ],
                    "duration": "3s",
                    "easing": "ease-in-out",
                    "delay": 1.4
                },
                {
                    "property": "opacity",
                    "values": [
                        0,
                        1,
                        1,
                        0
                    ],
                    "keyTimes": [
                        0,
                        0.2,
                        0.8,
                        1
                    ],
                    "duration": "3s",
                    "delay": 1.4
                }
            ]
        },
        "Pollen 2": {
            "animations": [
                {
                    "transform": "translate",
                    "values": [
                        0,
                        0,
                        8,
                        -4
                    ],
                    "duration": "3s",
                    "easing": "ease-in-out",
                    "delay": 1.75
                },
                {
                    "property": "opacity",
                    "values": [
                        0,
                        1,
                        1,
                        0
                    ],
                    "keyTimes": [
                        0,
                        0.2,
                        0.8,
                        1
                    ],
                    "duration": "3s",
                    "delay": 1.75
                }
            ]
        },
        "Pollen 1": {
            "animations": [
                {
                    "transform": "translate",
                    "values": [
                        0,
                        0,
                        8,
                        -4
                    ],
                    "duration": "3s",
                    "easing": "ease-in-out",
                    "delay": 2.0999999999999996
                },
                {
                    "property": "opacity",
                    "values": [
                        0,
                        1,
                        1,
                        0
                    ],
                    "keyTimes": [
                        0,
                        0.2,
                        0.8,
                        1
                    ],
                    "duration": "3s",
                    "delay": 2.0999999999999996
                }
            ]
        }
    }
}
